{
    "s": "http://schema.org/",
    "ex": "http://example.com/ns#",
    "xsd": "http://www.w3.org/2001/XMLSchema#",

    "url": "@id",

    "id": {
        "@id": "s:identifier",
        "@type": "xsd:integer"
    },
    "title": {
        "@id": "s:name",
        "@type": "xsd:string"
    },
    "author_association": {
        "@id": "ex:authorAssociation",
        "@type": "xsd:string"
    },
    "closed_at": {
        "@id": "s:endDate",
        "@type": "xsd:dateTimeStamp"
    },
    "creator": {
        "@id": "s:creator",
        "@type": "ex:User"
    },
    "user": {
        "@id": "s:url",
        "@type": "ex:User"
    },
    "assignees": {
         "@id": "s:assignee",
         "@type": "ex:User"
    },
    "issue": {
         "@id": "s:url",
         "@type": "ex:issue"
    },
    "name": {
        "@id": "s:name",
        "@type": "xsd:string"
    },
    "description": {
        "@id": "s:description",
        "@type": "xsd:string"
    },
    "issue_url": {
        "@type": "@id",
        "@reverse": "ex:comment"
    },
    "html_url": {
        "@id": "s:url",
        "@type": "xsd:anyURI"
    },
    "login": {
        "@id": "s:accountId",
        "@type": "xsd:string"
    },
    "repo_url": {
        "@type": "@id",
        "@reverse": "ex:issue"
    },
    "created_at": {
        "@id": "s:startDate",
        "@type": "xsd:dateTimeStamp"
    },
    "labels": {
        "@id": "s:name",
        "@type": "ex:label"
    },
    "comments_url": {
        "@id": "ex:comment",
        "@type": "s:url"
    },

    "state": "@type",
    "open": "ex:OpenIssue",
    "closed": "ex:ClosedIssue"
}